capepy/__init__.py
capepy/aws/__init__.py
capepy/aws/dynamodb.py
capepy/aws/glue.py
capepy/aws/lambda_.py
capepy/aws/meta.py
capepy/aws/utils.py
capepy-2.2.0.dist-info/LICENSE
capepy-2.2.0.dist-info/METADATA
capepy-2.2.0.dist-info/WHEEL
capepy-2.2.0.dist-info/RECORD
