Metadata-Version: 2.1
Name: capepy
Version: 2.2.0
Summary: A collection of utility functions useful for developing on and interacting with the CAPE infrastructure
License: Apache-2.0
Author: Micah Halter
Author-email: micah.halter@gtri.gatech.edu
Requires-Python: >=3.10,<4.0
Classifier: License :: OSI Approved :: Apache Software License
Classifier: Programming Language :: Python :: 3
Classifier: Programming Language :: Python :: 3.10
Classifier: Programming Language :: Python :: 3.11
Classifier: Programming Language :: Python :: 3.12
Classifier: Programming Language :: Python :: 3.13
